zigrun/.gitignore
zigrun/__init__.py
zigrun/__main__.py
zigrun/_version.py
zigrun/templates/main.zig.jinja2
zigrun-0.1.0.dist-info/LICENSE.txt
zigrun-0.1.0.dist-info/METADATA
zigrun-0.1.0.dist-info/WHEEL
zigrun-0.1.0.dist-info/entry_points.txt
zigrun-0.1.0.dist-info/top_level.txt
zigrun-0.1.0.dist-info/RECORD
