Metadata-Version: 2.1
Name: zigrun
Version: 0.1.0
Summary: A zig script runner
Author: Techcable
License: MIT License
Keywords: zig,runner,script,runner,development,repl
Classifier: Development Status :: 2 - Pre-Alpha
Classifier: Environment :: Console 
Classifier: Intended Audience :: Developers
Classifier: License :: OSI Approved :: MIT License
Classifier: Programming Language :: Python :: 3
Requires-Python: >=3.10
License-File: LICENSE.txt
Requires-Dist: jinja2
Requires-Dist: click
Requires-Dist: cloup
Provides-Extra: dev
Requires-Dist: mypy ; extra == 'dev'
Requires-Dist: black ; extra == 'dev'
Requires-Dist: isort ; extra == 'dev'
Provides-Extra: mypy
Requires-Dist: mypy (>=1) ; extra == 'mypy'
